{"nodes": [{"id": "d_al_mizan_lib_features_home_presentation_home_screen_dart", "label": "home_screen.dart", "file_type": "code", "source_file": "lib/features/home/presentation/home_screen.dart", "source_location": null}, {"id": "presentation_home_screen_homescreen", "label": "HomeScreen", "file_type": "code", "source_file": "lib/features/home/presentation/home_screen.dart", "source_location": null}, {"id": "consumerwidget", "label": "ConsumerWidget", "file_type": "code", "source_file": null, "source_location": null}, {"id": "modulesprovider", "label": "modulesProvider", "file_type": "code", "source_file": null, "source_location": null}, {"id": "streakprovider", "label": "streakProvider", "file_type": "code", "source_file": null, "source_location": null}, {"id": "usernameprovider", "label": "userNameProvider", "file_type": "code", "source_file": null, "source_location": null}, {"id": "presentation_home_screen_modulegridcard", "label": "_ModuleGridCard", "file_type": "code", "source_file": "lib/features/home/presentation/home_screen.dart", "source_location": null}, {"id": "statelesswidget", "label": "StatelessWidget", "file_type": "code", "source_file": null, "source_location": null}, {"id": "presentation_home_screen_quickactiontile", "label": "_QuickActionTile", "file_type": "code", "source_file": "lib/features/home/presentation/home_screen.dart", "source_location": null}, {"id": "presentation_home_screen_module", "label": "module", "file_type": "code", "source_file": "lib/features/home/presentation/home_screen.dart", "source_location": null}, {"id": "presentation_home_screen_icon", "label": "icon", "file_type": "code", "source_file": "lib/features/home/presentation/home_screen.dart", "source_location": null}, {"id": "icondata", "label": "IconData", "file_type": "code", "source_file": null, "source_location": null}, {"id": "presentation_home_screen_title", "label": "title", "file_type": "code", "source_file": "lib/features/home/presentation/home_screen.dart", "source_location": null}, {"id": "presentation_home_screen_subtitle", "label": "subtitle", "file_type": "code", "source_file": "lib/features/home/presentation/home_screen.dart", "source_location": null}, {"id": "presentation_home_screen_ontap", "label": "onTap", "file_type": "code", "source_file": "lib/features/home/presentation/home_screen.dart", "source_location": null}, {"id": "voidcallback", "label": "VoidCallback", "file_type": "code", "source_file": null, "source_location": null}, {"id": "presentation_home_screen_build", "label": "build", "file_type": "code", "source_file": "lib/features/home/presentation/home_screen.dart", "source_location": null}, {"id": "route_general_quiz", "label": "Route /general-quiz", "file_type": "concept", "source_file": null, "source_location": null}, {"id": "route_zakat", "label": "Route /zakat", "file_type": "concept", "source_file": null, "source_location": null}, {"id": "route_ask", "label": "Route /ask", "file_type": "concept", "source_file": null, "source_location": null}, {"id": "presentation_home_screen_iconformodule", "label": "_iconForModule", "file_type": "code", "source_file": "lib/features/home/presentation/home_screen.dart", "source_location": null}, {"id": "package_flutter_material_dart", "label": "package:flutter/material.dart", "file_type": "code", "source_file": null, "source_location": null}, {"id": "package_flutter_riverpod_flutter_riverpod_dart", "label": "package:flutter_riverpod/flutter_riverpod.dart", "file_type": "code", "source_file": null, "source_location": null}, {"id": "package_go_router_go_router_dart", "label": "package:go_router/go_router.dart", "file_type": "code", "source_file": null, "source_location": null}, {"id": "package_google_fonts_google_fonts_dart", "label": "package:google_fonts/google_fonts.dart", "file_type": "code", "source_file": null, "source_location": null}, {"id": "core_constants_app_constants_dart", "label": "../../../core/constants/app_constants.dart", "file_type": "code", "source_file": null, "source_location": null}, {"id": "core_constants_daily_quotes_dart", "label": "../../../core/constants/daily_quotes.dart", "file_type": "code", "source_file": null, "source_location": null}, {"id": "settings_providers_settings_provider_dart", "label": "../../settings/providers/settings_provider.dart", "file_type": "code", "source_file": null, "source_location": null}, {"id": "providers_home_provider_dart", "label": "../providers/home_provider.dart", "file_type": "code", "source_file": null, "source_location": null}], "edges": [{"source": "d_al_mizan_lib_features_home_presentation_home_screen_dart", "target": "presentation_home_screen_homescreen", "relation": "defines", "confidence": "EXTRACTED", "confidence_score": 1.0, "source_file": "lib/features/home/presentation/home_screen.dart", "source_location": null, "weight": 1.0}, {"source": "presentation_home_screen_homescreen", "target": "consumerwidget", "relation": "inherits", "confidence": "EXTRACTED", "confidence_score": 1.0, "source_file": "lib/features/home/presentation/home_screen.dart", "source_location": null, "weight": 1.0}, {"source": "presentation_home_screen_homescreen", "target": "modulesprovider", "relation": "references", "confidence": "EXTRACTED", "confidence_score": 1.0, "source_file": "lib/features/home/presentation/home_screen.dart", "source_location": null, "weight": 1.0, "context": "riverpod_reference"}, {"source": "presentation_home_screen_homescreen", "target": "streakprovider", "relation": "references", "confidence": "EXTRACTED", "confidence_score": 1.0, "source_file": "lib/features/home/presentation/home_screen.dart", "source_location": null, "weight": 1.0, "context": "riverpod_reference"}, {"source": "presentation_home_screen_homescreen", "target": "usernameprovider", "relation": "references", "confidence": "EXTRACTED", "confidence_score": 1.0, "source_file": "lib/features/home/presentation/home_screen.dart", "source_location": null, "weight": 1.0, "context": "riverpod_reference"}, {"source": "d_al_mizan_lib_features_home_presentation_home_screen_dart", "target": "presentation_home_screen_modulegridcard", "relation": "defines", "confidence": "EXTRACTED", "confidence_score": 1.0, "source_file": "lib/features/home/presentation/home_screen.dart", "source_location": null, "weight": 1.0}, {"source": "presentation_home_screen_modulegridcard", "target": "statelesswidget", "relation": "inherits", "confidence": "EXTRACTED", "confidence_score": 1.0, "source_file": "lib/features/home/presentation/home_screen.dart", "source_location": null, "weight": 1.0}, {"source": "d_al_mizan_lib_features_home_presentation_home_screen_dart", "target": "presentation_home_screen_quickactiontile", "relation": "defines", "confidence": "EXTRACTED", "confidence_score": 1.0, "source_file": "lib/features/home/presentation/home_screen.dart", "source_location": null, "weight": 1.0}, {"source": "presentation_home_screen_quickactiontile", "target": "statelesswidget", "relation": "inherits", "confidence": "EXTRACTED", "confidence_score": 1.0, "source_file": "lib/features/home/presentation/home_screen.dart", "source_location": null, "weight": 1.0}, {"source": "d_al_mizan_lib_features_home_presentation_home_screen_dart", "target": "presentation_home_screen_module", "relation": "defines", "confidence": "EXTRACTED", "confidence_score": 1.0, "source_file": "lib/features/home/presentation/home_screen.dart", "source_location": null, "weight": 1.0}, {"source": "d_al_mizan_lib_features_home_presentation_home_screen_dart", "target": "presentation_home_screen_icon", "relation": "defines", "confidence": "EXTRACTED", "confidence_score": 1.0, "source_file": "lib/features/home/presentation/home_screen.dart", "source_location": null, "weight": 1.0}, {"source": "d_al_mizan_lib_features_home_presentation_home_screen_dart", "target": "icondata", "relation": "references", "confidence": "EXTRACTED", "confidence_score": 1.0, "source_file": "lib/features/home/presentation/home_screen.dart", "source_location": null, "weight": 1.0, "context": "variable_type"}, {"source": "d_al_mizan_lib_features_home_presentation_home_screen_dart", "target": "presentation_home_screen_title", "relation": "defines", "confidence": "EXTRACTED", "confidence_score": 1.0, "source_file": "lib/features/home/presentation/home_screen.dart", "source_location": null, "weight": 1.0}, {"source": "d_al_mizan_lib_features_home_presentation_home_screen_dart", "target": "presentation_home_screen_subtitle", "relation": "defines", "confidence": "EXTRACTED", "confidence_score": 1.0, "source_file": "lib/features/home/presentation/home_screen.dart", "source_location": null, "weight": 1.0}, {"source": "d_al_mizan_lib_features_home_presentation_home_screen_dart", "target": "presentation_home_screen_ontap", "relation": "defines", "confidence": "EXTRACTED", "confidence_score": 1.0, "source_file": "lib/features/home/presentation/home_screen.dart", "source_location": null, "weight": 1.0}, {"source": "d_al_mizan_lib_features_home_presentation_home_screen_dart", "target": "voidcallback", "relation": "references", "confidence": "EXTRACTED", "confidence_score": 1.0, "source_file": "lib/features/home/presentation/home_screen.dart", "source_location": null, "weight": 1.0, "context": "variable_type"}, {"source": "d_al_mizan_lib_features_home_presentation_home_screen_dart", "target": "presentation_home_screen_build", "relation": "defines", "confidence": "EXTRACTED", "confidence_score": 1.0, "source_file": "lib/features/home/presentation/home_screen.dart", "source_location": null, "weight": 1.0}, {"source": "presentation_home_screen_build", "target": "modulesprovider", "relation": "references", "confidence": "EXTRACTED", "confidence_score": 1.0, "source_file": "lib/features/home/presentation/home_screen.dart", "source_location": null, "weight": 1.0, "context": "riverpod_reference"}, {"source": "presentation_home_screen_build", "target": "streakprovider", "relation": "references", "confidence": "EXTRACTED", "confidence_score": 1.0, "source_file": "lib/features/home/presentation/home_screen.dart", "source_location": null, "weight": 1.0, "context": "riverpod_reference"}, {"source": "presentation_home_screen_build", "target": "usernameprovider", "relation": "references", "confidence": "EXTRACTED", "confidence_score": 1.0, "source_file": "lib/features/home/presentation/home_screen.dart", "source_location": null, "weight": 1.0, "context": "riverpod_reference"}, {"source": "presentation_home_screen_build", "target": "route_general_quiz", "relation": "navigates", "confidence": "EXTRACTED", "confidence_score": 1.0, "source_file": "lib/features/home/presentation/home_screen.dart", "source_location": null, "weight": 1.0, "context": "route_path"}, {"source": "presentation_home_screen_build", "target": "route_zakat", "relation": "navigates", "confidence": "EXTRACTED", "confidence_score": 1.0, "source_file": "lib/features/home/presentation/home_screen.dart", "source_location": null, "weight": 1.0, "context": "route_path"}, {"source": "presentation_home_screen_build", "target": "route_ask", "relation": "navigates", "confidence": "EXTRACTED", "confidence_score": 1.0, "source_file": "lib/features/home/presentation/home_screen.dart", "source_location": null, "weight": 1.0, "context": "route_path"}, {"source": "d_al_mizan_lib_features_home_presentation_home_screen_dart", "target": "presentation_home_screen_modulegridcard", "relation": "defines", "confidence": "EXTRACTED", "confidence_score": 1.0, "source_file": "lib/features/home/presentation/home_screen.dart", "source_location": null, "weight": 1.0}, {"source": "d_al_mizan_lib_features_home_presentation_home_screen_dart", "target": "presentation_home_screen_iconformodule", "relation": "defines", "confidence": "EXTRACTED", "confidence_score": 1.0, "source_file": "lib/features/home/presentation/home_screen.dart", "source_location": null, "weight": 1.0}, {"source": "d_al_mizan_lib_features_home_presentation_home_screen_dart", "target": "presentation_home_screen_build", "relation": "defines", "confidence": "EXTRACTED", "confidence_score": 1.0, "source_file": "lib/features/home/presentation/home_screen.dart", "source_location": null, "weight": 1.0}, {"source": "d_al_mizan_lib_features_home_presentation_home_screen_dart", "target": "presentation_home_screen_quickactiontile", "relation": "defines", "confidence": "EXTRACTED", "confidence_score": 1.0, "source_file": "lib/features/home/presentation/home_screen.dart", "source_location": null, "weight": 1.0}, {"source": "d_al_mizan_lib_features_home_presentation_home_screen_dart", "target": "presentation_home_screen_build", "relation": "defines", "confidence": "EXTRACTED", "confidence_score": 1.0, "source_file": "lib/features/home/presentation/home_screen.dart", "source_location": null, "weight": 1.0}, {"source": "d_al_mizan_lib_features_home_presentation_home_screen_dart", "target": "package_flutter_material_dart", "relation": "imports", "confidence": "EXTRACTED", "confidence_score": 1.0, "source_file": "lib/features/home/presentation/home_screen.dart", "source_location": null, "weight": 1.0}, {"source": "d_al_mizan_lib_features_home_presentation_home_screen_dart", "target": "package_flutter_riverpod_flutter_riverpod_dart", "relation": "imports", "confidence": "EXTRACTED", "confidence_score": 1.0, "source_file": "lib/features/home/presentation/home_screen.dart", "source_location": null, "weight": 1.0}, {"source": "d_al_mizan_lib_features_home_presentation_home_screen_dart", "target": "package_go_router_go_router_dart", "relation": "imports", "confidence": "EXTRACTED", "confidence_score": 1.0, "source_file": "lib/features/home/presentation/home_screen.dart", "source_location": null, "weight": 1.0}, {"source": "d_al_mizan_lib_features_home_presentation_home_screen_dart", "target": "package_google_fonts_google_fonts_dart", "relation": "imports", "confidence": "EXTRACTED", "confidence_score": 1.0, "source_file": "lib/features/home/presentation/home_screen.dart", "source_location": null, "weight": 1.0}, {"source": "d_al_mizan_lib_features_home_presentation_home_screen_dart", "target": "core_constants_app_constants_dart", "relation": "imports", "confidence": "EXTRACTED", "confidence_score": 1.0, "source_file": "lib/features/home/presentation/home_screen.dart", "source_location": null, "weight": 1.0}, {"source": "d_al_mizan_lib_features_home_presentation_home_screen_dart", "target": "core_constants_daily_quotes_dart", "relation": "imports", "confidence": "EXTRACTED", "confidence_score": 1.0, "source_file": "lib/features/home/presentation/home_screen.dart", "source_location": null, "weight": 1.0}, {"source": "d_al_mizan_lib_features_home_presentation_home_screen_dart", "target": "settings_providers_settings_provider_dart", "relation": "imports", "confidence": "EXTRACTED", "confidence_score": 1.0, "source_file": "lib/features/home/presentation/home_screen.dart", "source_location": null, "weight": 1.0}, {"source": "d_al_mizan_lib_features_home_presentation_home_screen_dart", "target": "providers_home_provider_dart", "relation": "imports", "confidence": "EXTRACTED", "confidence_score": 1.0, "source_file": "lib/features/home/presentation/home_screen.dart", "source_location": null, "weight": 1.0}]}